{
  "extends": "../../api-extractor.json",
  "mainEntryPointFilePath": "./dist/packages/browser-performance/src/index.d.ts",
  "dtsRollup": {
    "publicTrimmedFilePath": "./dist/browser-performance.d.ts"
  },
  "compiler": {
    "overrideTsconfig": {
      "compilerOptions": {
        "baseUrl": "packages/browser-performance/dist/",
        "paths": {
          "@tracing/*": ["packages/*/src"]
        }
      },
      "include": ["global.d.ts", "packages/*/src/**/*.ts"],
      "exclude": ["test-utils/*"]
    }
  }
}
